LICENSE
MANIFEST.in
README.md
setup.py
django_mailto.egg-info/PKG-INFO
django_mailto.egg-info/SOURCES.txt
django_mailto.egg-info/dependency_links.txt
django_mailto.egg-info/not-zip-safe
django_mailto.egg-info/requires.txt
django_mailto.egg-info/top_level.txt
mailto/__init__.py
mailto/admin.py
mailto/forms.py
mailto/models.py
mailto/tasks.py
mailto/tests.py
mailto/urls.py
mailto/utils.py
mailto/views.py
mailto/management/__init__.py
mailto/static/mailto/css/mail.css
mailto/static/mailto/css/mail_editable.css
mailto/static/mailto/js/mail.js
mailto/templates/mailto/base.html
mailto/templates/mailto/base_site.html
mailto/templates/mailto/default.html
mailto/templates/mailto/default.txt
mailto/templates/mailto/default_2col.html
mailto/templates/mailto/default_3col.html
mailto/templates/mailto/includes/placeholder.html
mailto/templatetags/__init__.py
mailto/templatetags/mailtotags.py