Metadata-Version: 1.1
Name: django-mailto
Version: 0.1.0
Summary: Django app to send, manage and queue multilingual mails with template support.
Home-page: https://github.com/hckjck/django-mailto
Author: Michael Handerek
Author-email: michael@handerek.net
License: BSD
Platform: UNKNOWN
Classifier: Development Status :: 5 - Production/Stable
Classifier: Environment :: Web Environment
Classifier: Framework :: Django
Classifier: Intended Audience :: Developers
Classifier: License :: OSI Approved :: BSD License
Classifier: Operating System :: OS Independent
Classifier: Programming Language :: Python
Classifier: Programming Language :: Python :: 2
Classifier: Programming Language :: Python :: 2.6
Classifier: Programming Language :: Python :: 2.7
Classifier: Programming Language :: Python :: 3
Classifier: Programming Language :: Python :: 3.2
Classifier: Programming Language :: Python :: 3.3
Classifier: Topic :: Internet :: WWW/HTTP
